authzed/api/materialize/v0/__init__.py
authzed/api/materialize/v0/__init__.pyi
authzed/api/materialize/v0/watchpermissions_pb2.py
authzed/api/materialize/v0/watchpermissions_pb2.pyi
authzed/api/materialize/v0/watchpermissions_pb2_grpc.py
authzed/api/materialize/v0/watchpermissions_pb2_grpc.pyi
authzed/api/materialize/v0/watchpermissionsets_pb2.py
authzed/api/materialize/v0/watchpermissionsets_pb2.pyi
authzed/api/materialize/v0/watchpermissionsets_pb2_grpc.py
authzed/api/materialize/v0/watchpermissionsets_pb2_grpc.pyi
authzed/api/v0/core_pb2.py
authzed/api/v0/core_pb2.pyi
authzed/api/v0/core_pb2_grpc.py
authzed/api/v0/core_pb2_grpc.pyi
authzed/api/v0/developer_pb2.py
authzed/api/v0/developer_pb2.pyi
authzed/api/v0/developer_pb2_grpc.py
authzed/api/v0/developer_pb2_grpc.pyi
authzed/api/v1/__init__.py
authzed/api/v1/__init__.pyi
authzed/api/v1/core_pb2.py
authzed/api/v1/core_pb2.pyi
authzed/api/v1/core_pb2_grpc.py
authzed/api/v1/core_pb2_grpc.pyi
authzed/api/v1/debug_pb2.py
authzed/api/v1/debug_pb2.pyi
authzed/api/v1/debug_pb2_grpc.py
authzed/api/v1/debug_pb2_grpc.pyi
authzed/api/v1/error_reason_pb2.py
authzed/api/v1/error_reason_pb2.pyi
authzed/api/v1/error_reason_pb2_grpc.py
authzed/api/v1/error_reason_pb2_grpc.pyi
authzed/api/v1/experimental_service_pb2.py
authzed/api/v1/experimental_service_pb2.pyi
authzed/api/v1/experimental_service_pb2_grpc.py
authzed/api/v1/experimental_service_pb2_grpc.pyi
authzed/api/v1/openapi_pb2.py
authzed/api/v1/openapi_pb2.pyi
authzed/api/v1/openapi_pb2_grpc.py
authzed/api/v1/openapi_pb2_grpc.pyi
authzed/api/v1/permission_service_pb2.py
authzed/api/v1/permission_service_pb2.pyi
authzed/api/v1/permission_service_pb2_grpc.py
authzed/api/v1/permission_service_pb2_grpc.pyi
authzed/api/v1/schema_service_pb2.py
authzed/api/v1/schema_service_pb2.pyi
authzed/api/v1/schema_service_pb2_grpc.py
authzed/api/v1/schema_service_pb2_grpc.pyi
authzed/api/v1/watch_service_pb2.py
authzed/api/v1/watch_service_pb2.pyi
authzed/api/v1/watch_service_pb2_grpc.py
authzed-1.24.0.dist-info/WHEEL
authzed-1.24.0.dist-info/METADATA
authzed-1.24.0.dist-info/RECORD
