Metadata-Version: 2.3
Name: authzed
Version: 1.24.0
Summary: Client library for SpiceDB.
Author: Authzed
Author-email: Authzed <support@authzed.com>
Requires-Dist: grpcio~=1.63
Requires-Dist: protobuf>=5.26,<7
Requires-Dist: grpc-interceptor>=0.15.4,<0.16
Requires-Dist: googleapis-common-protos>=1.65.0,<2
Requires-Dist: protovalidate>=0.7.1,<1.1.0
Requires-Python: >=3.9, <4
